utils/__init__.py
utils/_paths.py
utils/legend.py
utils/rgb_ind_convertor.py
utils/util.py
Deep_floorplan-0.0.0.dist-info/LICENSE
Deep_floorplan-0.0.0.dist-info/METADATA
Deep_floorplan-0.0.0.dist-info/WHEEL
Deep_floorplan-0.0.0.dist-info/top_level.txt
Deep_floorplan-0.0.0.dist-info/RECORD
